q_logger_py/__init__.py
q_logger_py/handler/__init__.py
q_logger_py/handler/queue_handler.py
q_logger_py/worker/__init__.py
q_logger_py/worker/base_thread_worker.py
q_logger_py/worker/thread_file_worker.py
q_logger_py/worker/thread_stdout_worker.py
q_logger_py-0.0.3.dist-info/LICENSE
q_logger_py-0.0.3.dist-info/METADATA
q_logger_py-0.0.3.dist-info/WHEEL
q_logger_py-0.0.3.dist-info/top_level.txt
q_logger_py-0.0.3.dist-info/RECORD
