Metadata-Version: 2.1
Name: q-logger-py
Version: 0.0.3
Summary: Pure Python 3 logging library that use queues for handling log.
Author-email: minwook-shin <minwook0106@gmail.com>
Project-URL: Homepage, https://github.com/minwook-shin/q-logger-py
Project-URL: Bug Tracker, https://github.com/minwook-shin/q-logger-py/issues
Classifier: Programming Language :: Python :: 3
Classifier: License :: OSI Approved :: Apache Software License
Classifier: Operating System :: OS Independent
Requires-Python: >=3.9
License-File: LICENSE
Provides-Extra: dev
Requires-Dist: build ==1.1.1 ; extra == 'dev'
